MANIFEST.in
README.rst
setup.py
docs/HISTORY.txt
docs/LICENSE.GPL
docs/LICENSE.txt
ftw/__init__.py
ftw.workspace.egg-info/PKG-INFO
ftw.workspace.egg-info/SOURCES.txt
ftw.workspace.egg-info/dependency_links.txt
ftw.workspace.egg-info/entry_points.txt
ftw.workspace.egg-info/namespace_packages.txt
ftw.workspace.egg-info/not-zip-safe
ftw.workspace.egg-info/requires.txt
ftw.workspace.egg-info/top_level.txt
ftw/workspace/__init__.py
ftw/workspace/config.py
ftw/workspace/configure.zcml
ftw/workspace/export.py
ftw/workspace/indexers.py
ftw/workspace/interfaces.py
ftw/workspace/lawgiver.zcml
ftw/workspace/quick_upload.py
ftw/workspace/setuphandlers.py
ftw/workspace/testing.py
ftw/workspace/utils.py
ftw/workspace/vocabularies.py
ftw/workspace/zip_export.py
ftw/workspace/zip_extract.py
ftw/workspace/browser/__init__.py
ftw/workspace/browser/configure.zcml
ftw/workspace/browser/documents.pt
ftw/workspace/browser/documents.py
ftw/workspace/browser/events.pt
ftw/workspace/browser/events.py
ftw/workspace/browser/eventscalendar.pt
ftw/workspace/browser/helper.py
ftw/workspace/browser/move_items.py
ftw/workspace/browser/overview.pt
ftw/workspace/browser/overview.py
ftw/workspace/browser/overview_sublisting.pt
ftw/workspace/browser/overview_sublisting.py
ftw/workspace/browser/preview.py
ftw/workspace/browser/preview_tab.pt
ftw/workspace/browser/previews.pt
ftw/workspace/browser/tab.py
ftw/workspace/browser/workspaces.py
ftw/workspace/browser/previews/__init__.py
ftw/workspace/browser/previews/configure.zcml
ftw/workspace/browser/previews/default.py
ftw/workspace/browser/previews/ftwfile.py
ftw/workspace/browser/previews/image.py
ftw/workspace/browser/previews/misc.py
ftw/workspace/browser/previews/office.py
ftw/workspace/browser/resources/default.png
ftw/workspace/browser/resources/doc.png
ftw/workspace/browser/resources/docx.png
ftw/workspace/browser/resources/icon_function_remove.gif
ftw/workspace/browser/resources/icon_object_folder.gif
ftw/workspace/browser/resources/icon_object_workspace.gif
ftw/workspace/browser/resources/pdf.png
ftw/workspace/browser/resources/ppt.png
ftw/workspace/browser/resources/pptx.png
ftw/workspace/browser/resources/preview.css
ftw/workspace/browser/resources/preview.js
ftw/workspace/browser/resources/txt.png
ftw/workspace/browser/resources/xls.png
