Metadata-Version: 2.1
Name: ftw.workspace
Version: 4.3.0
Summary: A project folder for plone.
Home-page: https://github.com/4teamwork/ftw.workspace
Author: 4teamwork AG
Author-email: mailto:info@4teamwork.ch
License: GPL2
Keywords: ftw workspace project folder plone
Platform: UNKNOWN
Classifier: Framework :: Plone
Classifier: Framework :: Plone :: 4.3
Classifier: Programming Language :: Python
Classifier: Topic :: Software Development :: Libraries :: Python Modules
Provides-Extra: zip_export
Provides-Extra: contact
Provides-Extra: zip_extract
Provides-Extra: tests
